gaphor/C4Model/__init__.py
gaphor/C4Model/c4model.py
gaphor/C4Model/diagramitems/__init__.py
gaphor/C4Model/diagramitems/container.py
gaphor/C4Model/diagramitems/database.py
gaphor/C4Model/diagramitems/dependency.py
gaphor/C4Model/diagramitems/person.py
gaphor/C4Model/iconname.py
gaphor/C4Model/modelinglanguage.py
gaphor/C4Model/propertypages.py
gaphor/C4Model/propertypages.ui
gaphor/C4Model/toolbox.py
gaphor/RAAML/__init__.py
gaphor/RAAML/diagram_svgs/__init__.py
gaphor/RAAML/diagram_svgs/and.svg
gaphor/RAAML/diagram_svgs/basic_event.svg
gaphor/RAAML/diagram_svgs/conditional_event.svg
gaphor/RAAML/diagram_svgs/dormant_event.svg
gaphor/RAAML/diagram_svgs/house_event.svg
gaphor/RAAML/diagram_svgs/inhibit.svg
gaphor/RAAML/diagram_svgs/majority_vote.svg
gaphor/RAAML/diagram_svgs/not.svg
gaphor/RAAML/diagram_svgs/or.svg
gaphor/RAAML/diagram_svgs/seq.svg
gaphor/RAAML/diagram_svgs/transfer_in.svg
gaphor/RAAML/diagram_svgs/xor.svg
gaphor/RAAML/diagram_svgs/zero_event.svg
gaphor/RAAML/diagramitems.py
gaphor/RAAML/fta/__init__.py
gaphor/RAAML/fta/andgate.py
gaphor/RAAML/fta/basicevent.py
gaphor/RAAML/fta/conditionalevent.py
gaphor/RAAML/fta/constants.py
gaphor/RAAML/fta/dormantevent.py
gaphor/RAAML/fta/ftatoolbox.py
gaphor/RAAML/fta/houseevent.py
gaphor/RAAML/fta/inhibitgate.py
gaphor/RAAML/fta/intermediateevent.py
gaphor/RAAML/fta/majorityvotegate.py
gaphor/RAAML/fta/notgate.py
gaphor/RAAML/fta/orgate.py
gaphor/RAAML/fta/seqgate.py
gaphor/RAAML/fta/topevent.py
gaphor/RAAML/fta/transferin.py
gaphor/RAAML/fta/transferout.py
gaphor/RAAML/fta/undevelopedevent.py
gaphor/RAAML/fta/xorgate.py
gaphor/RAAML/fta/zeroevent.py
gaphor/RAAML/modelinglanguage.py
gaphor/RAAML/raaml.py
gaphor/RAAML/stpa/__init__.py
gaphor/RAAML/stpa/block.py
gaphor/RAAML/stpa/controlaction.py
gaphor/RAAML/stpa/operationalsituation.py
gaphor/RAAML/stpa/relationships.py
gaphor/RAAML/stpa/stpatoolbox.py
gaphor/RAAML/stpa/unsafecontrolaction.py
gaphor/RAAML/toolbox.py
gaphor/SysML/__init__.py
gaphor-3.2.0.dist-info/METADATA
gaphor-3.2.0.dist-info/WHEEL
gaphor-3.2.0.dist-info/entry_points.txt
gaphor-3.2.0.dist-info/licenses/LICENSES/Apache-2.0.txt
gaphor-3.2.0.dist-info/licenses/LICENSES/BSD-3-Clause.txt
gaphor-3.2.0.dist-info/licenses/LICENSES/GPL-2.0-or-later.txt
gaphor-3.2.0.dist-info/licenses/LICENSES/LGPL-2.1-or-later.txt
gaphor-3.2.0.dist-info/RECORD
