Metadata-Version: 2.4
Name: gaphor
Version: 3.2.0
Summary: Gaphor is the simple modeling tool written in Python.
License-File: LICENSES/Apache-2.0.txt
License-File: LICENSES/BSD-3-Clause.txt
License-File: LICENSES/GPL-2.0-or-later.txt
License-File: LICENSES/LGPL-2.1-or-later.txt
Keywords: GTK,diagram,UML,MBSE,modeling
Author: Arjan Molenaar
Author-email: gaphor@gmail.com
Requires-Python: >=3.12,<3.15
Classifier: Development Status :: 5 - Production/Stable
Classifier: Environment :: X11 Applications :: GTK
Classifier: Environment :: MacOS X
Classifier: Environment :: Win32 (MS Windows)
Classifier: Intended Audience :: Developers
Classifier: Intended Audience :: End Users/Desktop
Classifier: Intended Audience :: Information Technology
Classifier: License :: OSI Approved :: Apache Software License
Classifier: Operating System :: MacOS :: MacOS X
Classifier: Operating System :: Microsoft :: Windows
Classifier: Operating System :: POSIX
Classifier: Operating System :: Unix
Classifier: Programming Language :: Python
Classifier: Topic :: Desktop Environment :: Gnome
Classifier: Topic :: Multimedia :: Graphics :: Editors :: Vector-Based
Classifier: Topic :: Software Development :: Documentation
Requires-Dist: PyGObject (>=3.52)
Requires-Dist: babel (>=2.10.3)
Requires-Dist: better-exceptions (>=0.3.3)
Requires-Dist: defusedxml (>=0.7.1)
Requires-Dist: dulwich (>=0.21.7,<0.23.0)
Requires-Dist: gaphas (>=5.0)
Requires-Dist: generic (>=1.0.0)
Requires-Dist: jedi (>=0.18.1,<0.20.0)
Requires-Dist: pillow (>=10.0.0)
Requires-Dist: pycairo (>=1.22.0)
Requires-Dist: pydot (>=1.4.2,<4.0.0)
Requires-Dist: pyobjc-framework-cocoa (>=9.0.1,<11.0.0) ; sys_platform == "darwin"
Requires-Dist: tinycss2 (>=1.0.2)
Project-URL: Documentation, https://docs.gaphor.org/
Project-URL: Homepage, https://gaphor.org/
Project-URL: Repository, https://github.com/gaphor/gaphor
